locknotey/__init__.py
locknotey/locknotey.py
locknotey-0.2.0.dist-info/licenses/AUTHORS.md
locknotey-0.2.0.dist-info/licenses/LICENSE.txt
locknotey-0.2.0.dist-info/METADATA
locknotey-0.2.0.dist-info/WHEEL
locknotey-0.2.0.dist-info/entry_points.txt
locknotey-0.2.0.dist-info/top_level.txt
locknotey-0.2.0.dist-info/RECORD
