Metadata-Version: 2.4
Name: locknotey
Version: 0.2.0
Summary: Simple script that stores encrypted data within itself and allows you to modify it using any editor.
Home-page: https://github.com/devbisme/locknotey
Author: Dave Vandenbout
Author-email: devb@xess.com
License: MIT
Platform: Linux
Classifier: Development Status :: 3 - Alpha
Classifier: Programming Language :: Python
Classifier: Intended Audience :: End Users/Desktop
Classifier: License :: OSI Approved :: MIT License
Classifier: Operating System :: POSIX :: Linux
Classifier: Topic :: Utilities
Requires-Python: >=3.8
License-File: LICENSE.txt
License-File: AUTHORS.md
Requires-Dist: importlib-metadata
Requires-Dist: cryptography==3.0
Requires-Dist: FreeSimpleGUI
Provides-Extra: testing
Requires-Dist: setuptools; extra == "testing"
Requires-Dist: pytest; extra == "testing"
Requires-Dist: pytest-cov; extra == "testing"
Dynamic: license-file
